pygeojson/__init__.py
pygeojson/deserializers.py
pygeojson/py.typed
pygeojson/serializers.py
pygeojson/types.py
pygeojson-0.2.0.dist-info/WHEEL
pygeojson-0.2.0.dist-info/METADATA
pygeojson-0.2.0.dist-info/RECORD
