Metadata-Version: 2.1
Name: pygeojson
Version: 0.2.0
Summary: GeoJSON library for Python with types
Home-page: https://github.com/hawkaa/pygeojson
License: MIT
Keywords: geojson,typed,dataclasses,immutable
Author: Håkon Åmdal
Author-email: hakon@aamdal.com
Maintainer: Håkon Åmdal
Maintainer-email: hakon@aamdal.com
Requires-Python: >=3.7,<4.0
Classifier: Development Status :: 4 - Beta
Classifier: Intended Audience :: Developers
Classifier: License :: OSI Approved :: MIT License
Classifier: Programming Language :: Python :: 3
Classifier: Programming Language :: Python :: 3.7
Classifier: Programming Language :: Python :: 3.8
Classifier: Topic :: Scientific/Engineering :: GIS
Classifier: Topic :: Software Development :: Libraries
Classifier: Typing :: Typed
Project-URL: Documentation, https://github.com/hawkaa/pygeojson
Project-URL: Repository, https://github.com/hawkaa/pygeojson
